percentile/__init__.py
percentile/percentile.py
percentile-1.0.3.dist-info/LICENSE
percentile-1.0.3.dist-info/METADATA
percentile-1.0.3.dist-info/NOTICE
percentile-1.0.3.dist-info/WHEEL
percentile-1.0.3.dist-info/top_level.txt
percentile-1.0.3.dist-info/RECORD
