Metadata-Version: 2.1
Name: percentile
Version: 1.0.3
Summary: Plotting CDF tail percentiles
Home-page: http://github.com/nicmcd/percentile
Author: Nic McDonald
Author-email: nicci02@hotmail.com
License: BSD
Platform: UNKNOWN
